twitauth/__init__.py
twitauth/twitter.py
twitauth/twitter_model.py
twitauth-0.0.1.dist-info/METADATA
twitauth-0.0.1.dist-info/RECORD
twitauth-0.0.1.dist-info/WHEEL
twitauth-0.0.1.dist-info/top_level.txt
