Metadata-Version: 2.1
Name: twitauth
Version: 0.0.1
Summary: A library to automatically integrate twitter login with database compatibility
Home-page: https://github.com/anish12341/twitauth.git
Author: Anish Patel
Author-email: anishpatel345@gmail.com
License: UNKNOWN
Platform: UNKNOWN
